{
    "CreatedDate": "2017-04-09T03:04:00",
    "ModifiedDate": "2017-04-09T03:04:00",
    "CustomerKey": "25541",
    "Name": "API Trigger Demo Welcome",
    "Description": "API Trigger Demo Welcome",
    "Keyword": "",
    "SendClassification": {
        "CustomerKey": "Default Commercial"
    },
    "SenderProfile": {
        "CustomerKey": "124"
    },
    "FromName": "Make Positive",
    "FromAddress": "kim.hellbom@makepositive.com",
    "SuppressTracking": "false",
    "TriggeredSendType": "Continuous",
    "TriggeredSendStatus": "Active",
    "AutoAddSubscribers": "true",
    "AutoUpdateSubscribers": "false",
    "BatchInterval": "0",
    "BccEmail": "",
    "EmailSubject": "API Demo Email",
    "DynamicEmailSubject": "API Demo Email",
    "IsMultipart": "false",
    "IsWrapped": "true",
    "AllowedSlots": "0",
    "NewSlotTrigger": "0",
    "Priority": "4",
    "r__folder_Path": "Triggered Sends",
    "r__assetMessage_Name": "Newsletter API Demo",
    "r__assetMessage_Key": "f518f5cd-f04c-42cb-b9d6-b0946322287c",
    "r__list_PathName": "my subscribers/All Subscribers"
}
