{
    "customerKey": "ac014a23-d27c-4895-8995-36ca92085ee1",
    "contentType": "text/html",
    "assetType": {
        "name": "webpage",
        "displayName": "Web Page"
    },
    "version": 1,
    "name": "Survey",
    "owner": {
        "email": "saransh.garg@makepositive.com",
        "name": "Saransh Garg"
    },
    "createdDate": "2020-01-23T03:42:31.353-06:00",
    "createdBy": {
        "email": "saransh.garg@makepositive.com",
        "name": "Saransh Garg"
    },
    "modifiedDate": "2020-01-23T03:42:31.353-06:00",
    "modifiedBy": {
        "email": "saransh.garg@makepositive.com",
        "name": "Saransh Garg"
    },
    "status": {
        "name": "Draft"
    },
    "meta": {
        "globalStyles": {
            "isLocked": false,
            "body": {
                "max-width": "1280px"
            }
        }
    },
    "views": {
        "html": {
            "thumbnail": {},
            "meta": {},
            "slots": {
                "header": {
                    "design": "<p style=\"font-family:arial;color:#ccc;font-size:11px;text-align:center;vertical-align:middle;font-weight:bold;padding:10px;margin:0;border:#ccc dashed 1px;\">Drop blocks or content here</p>",
                    "modelVersion": 2
                },
                "footer": {
                    "design": "<p style=\"font-family:arial;color:#ccc;font-size:11px;text-align:center;vertical-align:middle;font-weight:bold;padding:10px;margin:0;border:#ccc dashed 1px;\">Drop blocks or content here</p>",
                    "modelVersion": 2
                },
                "col1": {
                    "design": "<p style=\"font-family:arial;color:#ccc;font-size:11px;text-align:center;vertical-align:middle;font-weight:bold;padding:10px;margin:0;border:#ccc dashed 1px;\">Drop blocks or content here</p>",
                    "modelVersion": 2
                }
            },
            "modelVersion": 2
        }
    },
    "availableViews": [
        "html"
    ],
    "modelVersion": 2,
    "r__folder_Path": "Content Builder"
}
